{
    "data": [
        {
            "code": "BOM",
            "name": "Chhatrapati Shivaji International Airport",
            "city": "Mumbai"
        },
        {
            "code": "GOI",
            "name": "Dabolim Airport",
            "city": "Goa"
        },
        {
            "code": "BHJ",
            "name": "Bhuj Airport",
            "city": "Bhuj"
        },
        {
            "code": "DEL",
            "name": "Indira Gandhi International Airport",
            "city": "New Delhi"
        }
    ]
}
